pyisotopomer/SPnonlineq.py
pyisotopomer/__init__.py
pyisotopomer/algebraic_gk_eqns.py
pyisotopomer/automate_gk_eqns.py
pyisotopomer/automate_gk_solver.py
pyisotopomer/calcSPmain.py
pyisotopomer/calcdeltaSP.py
pyisotopomer/calculate_17R.py
pyisotopomer/calculate_17R_v2.py
pyisotopomer/check31r.py
pyisotopomer/constants_new.py
pyisotopomer/isotopestandards.py
pyisotopomer/isotopomerinput.py
pyisotopomer/parseoutput.py
pyisotopomer/pyisotopomer.py
pyisotopomer/scramblinginput.py
pyisotopomer/tracerSPmain.py
pyisotopomer/tracerinput.py
pyisotopomer/tracernonlineq.py
pyisotopomer-1.0.4.dist-info/LICENSE
pyisotopomer-1.0.4.dist-info/METADATA
pyisotopomer-1.0.4.dist-info/WHEEL
pyisotopomer-1.0.4.dist-info/top_level.txt
pyisotopomer-1.0.4.dist-info/RECORD
