Metadata-Version: 2.1
Name: pyisotopomer
Version: 1.0.4
Summary: Nitrous oxide isotopocule data corrections in Python
Home-page: https://github.com/ckelly314/pyisotopomer
Author: Colette L. Kelly
Author-email: clkelly@stanford.edu
Project-URL: Bug Tracker, https://github.com/ckelly314/pyisotopomer/issues
Classifier: Development Status :: 4 - Beta
Classifier: Programming Language :: Python :: 3
Classifier: License :: OSI Approved :: MIT License
Classifier: Operating System :: OS Independent
Classifier: Natural Language :: English
Classifier: Intended Audience :: Science/Research
Classifier: Topic :: Scientific/Engineering :: Chemistry
License-File: LICENSE
Requires-Dist: numpy
Requires-Dist: pandas
Requires-Dist: scipy
Requires-Dist: datetime
Requires-Dist: openpyxl
Requires-Dist: jupyter
